Metadata-Version: 2.1
Name: linenotif
Version: 1.0.4
Summary: Easy LINE-Notify syntax
Home-page: https://github.com/MasterIceZ/LineNotify
Author: Borworntat Dendumrongkul
Author-email: borworntat.d@gmail.com
License: MIT
Download-URL: https://github.com/MasterIceZ/LineNotify/archive/v_104.tar.gz
Keywords: LINE
Platform: UNKNOWN
Classifier: Development Status :: 3 - Alpha
Classifier: Intended Audience :: Developers
Classifier: Topic :: Software Development :: Build Tools
Classifier: License :: OSI Approved :: MIT License
Classifier: Programming Language :: Python :: 3.9
License-File: LICENSE
